openzim_uploader/__init__.py
openzim_uploader-1.2.dist-info/METADATA
openzim_uploader-1.2.dist-info/WHEEL
openzim_uploader-1.2.dist-info/entry_points.txt
openzim_uploader-1.2.dist-info/top_level.txt
openzim_uploader-1.2.dist-info/zip-safe
openzim_uploader-1.2.dist-info/RECORD
