Metadata-Version: 2.1
Name: openzim-uploader
Version: 1.2
Summary: SCP/SFTP helper for openZIM uploads to our dropbox
Home-page: https://github.com/openzim/zimfarm/tree/master/uploader
Author: kiwix
Author-email: reg@kiwix.org
License: GPLv3+
Keywords: scp sftp upload kiwix
Platform: UNKNOWN
Classifier: Development Status :: 5 - Production/Stable
Classifier: Intended Audience :: Developers
Classifier: Programming Language :: Python
Classifier: Programming Language :: Python :: 3.6
Classifier: Programming Language :: Python :: 3.7
Classifier: Programming Language :: Python :: 3.8
Classifier: Programming Language :: Python :: 3.9
Classifier: Programming Language :: Python :: 3.10
Classifier: License :: OSI Approved :: GNU General Public License v3 or later (GPLv3+)
Requires-Python: >=3.6
Requires-Dist: kiwixstorage (<0.9,>=0.8.3)
Provides-Extra: all
Requires-Dist: humanfriendly (>=8.0) ; extra == 'all'
